fastapi_users_pelicanq/__init__.py
fastapi_users_pelicanq/exceptions.py
fastapi_users_pelicanq/fastapi_users.py
fastapi_users_pelicanq/jwt.py
fastapi_users_pelicanq/manager.py
fastapi_users_pelicanq/models.py
fastapi_users_pelicanq/openapi.py
fastapi_users_pelicanq/password.py
fastapi_users_pelicanq/py.typed
fastapi_users_pelicanq/schemas.py
fastapi_users_pelicanq/types.py
fastapi_users_pelicanq/authentication/__init__.py
fastapi_users_pelicanq/authentication/authenticator.py
fastapi_users_pelicanq/authentication/backend.py
fastapi_users_pelicanq/authentication/strategy/__init__.py
fastapi_users_pelicanq/authentication/strategy/base.py
fastapi_users_pelicanq/authentication/strategy/jwt.py
fastapi_users_pelicanq/authentication/strategy/redis.py
fastapi_users_pelicanq/authentication/strategy/db/__init__.py
fastapi_users_pelicanq/authentication/strategy/db/adapter.py
fastapi_users_pelicanq/authentication/strategy/db/models.py
fastapi_users_pelicanq/authentication/strategy/db/strategy.py
fastapi_users_pelicanq/authentication/transport/__init__.py
fastapi_users_pelicanq/authentication/transport/base.py
fastapi_users_pelicanq/authentication/transport/bearer.py
fastapi_users_pelicanq/authentication/transport/cookie.py
fastapi_users_pelicanq/db/__init__.py
fastapi_users_pelicanq/db/base.py
fastapi_users_pelicanq/router/__init__.py
fastapi_users_pelicanq/router/auth.py
fastapi_users_pelicanq/router/common.py
fastapi_users_pelicanq/router/oauth.py
fastapi_users_pelicanq/router/register.py
fastapi_users_pelicanq/router/reset.py
fastapi_users_pelicanq/router/users.py
fastapi_users_pelicanq/router/verify.py
fastapi_users_pelicanq-13.0.5.dist-info/METADATA
fastapi_users_pelicanq-13.0.5.dist-info/WHEEL
fastapi_users_pelicanq-13.0.5.dist-info/licenses/LICENSE
fastapi_users_pelicanq-13.0.5.dist-info/RECORD
