Metadata-Version: 2.3
Name: fastapi-users-pelicanq
Version: 13.0.5
Summary: Fork for small edit of original package.
Project-URL: Documentation, https://fastapi-users.github.io/fastapi-users/
Project-URL: Source, https://github.com/fastapi-users/fastapi-users
Author-email: François Voron <fvoron@gmail.com>
License-File: LICENSE
Classifier: Development Status :: 5 - Production/Stable
Classifier: Framework :: AsyncIO
Classifier: Framework :: FastAPI
Classifier: Intended Audience :: Developers
Classifier: License :: OSI Approved :: MIT License
Classifier: Programming Language :: Python :: 3 :: Only
Classifier: Programming Language :: Python :: 3.8
Classifier: Programming Language :: Python :: 3.9
Classifier: Programming Language :: Python :: 3.10
Classifier: Programming Language :: Python :: 3.11
Classifier: Programming Language :: Python :: 3.12
Classifier: Topic :: Internet :: WWW/HTTP :: Session
Requires-Python: >=3.8
Requires-Dist: email-validator<2.3,>=1.1.0
Requires-Dist: fastapi>=0.65.2
Requires-Dist: makefun<2.0.0,>=1.11.2
Requires-Dist: pwdlib[argon2,bcrypt]==0.2.0
Requires-Dist: pyjwt[crypto]==2.8.0
Requires-Dist: python-multipart==0.0.9
Provides-Extra: beanie
Requires-Dist: fastapi-users-db-beanie>=3.0.0; extra == 'beanie'
Provides-Extra: oauth
Requires-Dist: httpx-oauth>=0.13; extra == 'oauth'
Provides-Extra: redis
Requires-Dist: redis<6.0.0,>=4.3.3; extra == 'redis'
Provides-Extra: sqlalchemy
Requires-Dist: fastapi-users-db-sqlalchemy>=6.0.0; extra == 'sqlalchemy'
